moddr/__init__.py
moddr/embedding_state.py
moddr/evaluation/__init__.py
moddr/evaluation/evaluation.py
moddr/processing/__init__.py
moddr/processing/processing.py
moddr/visualization/__init__.py
moddr/visualization/visualization.py
moddr-1.0.0.dist-info/METADATA
moddr-1.0.0.dist-info/WHEEL
moddr-1.0.0.dist-info/licenses/LICENSE
moddr-1.0.0.dist-info/RECORD
