Metadata-Version: 2.4
Name: moddr
Version: 1.0.0
Summary: This package allows the refinement of DR-based positions with respect to certain data features.
Project-URL: Homepage, https://github.com/kohaupt/moddr
Project-URL: Repository, https://github.com/kohaupt/moddr
Project-URL: Issues, https://github.com/kohaupt/moddr/issues
Author-email: Konstantin Haupt <konstantin.haupt@study.hs-duesseldorf.de>
License: MIT License
License-File: LICENSE
Classifier: License :: OSI Approved :: MIT License
Classifier: Operating System :: MacOS
Classifier: Operating System :: Microsoft :: Windows
Classifier: Operating System :: POSIX
Classifier: Operating System :: Unix
Classifier: Programming Language :: Python :: 3
Classifier: Programming Language :: Python :: 3.10
Classifier: Programming Language :: Python :: 3.11
Classifier: Programming Language :: Python :: 3.12
Requires-Python: >=3.10
Requires-Dist: bokeh>=3.4.3
Requires-Dist: colorcet>=3.1.0
Requires-Dist: dash>=2.18.2
Requires-Dist: datashader>=0.17.0
Requires-Dist: holoviews>=1.20.1
Requires-Dist: igraph>=0.11.9
Requires-Dist: leidenalg>=0.10.2
Requires-Dist: matplotlib>=3.9.4
Requires-Dist: nbformat>=5.10.4
Requires-Dist: networkx>=3.0
Requires-Dist: numpy>=1.26.0
Requires-Dist: pandas>=2.2.3
Requires-Dist: scikit-image>=0.24.0
Requires-Dist: scikit-learn>=1.6.1
Requires-Dist: seaborn>=0.13.2
Requires-Dist: umap-learn>=0.5.7
Provides-Extra: dev
Requires-Dist: ipykernel>=6.29.5; extra == 'dev'
Requires-Dist: ipywidgets>=8.1.5; extra == 'dev'
Requires-Dist: pytest>=8.3.4; extra == 'dev'
Requires-Dist: ucimlrepo>=0.0.7; extra == 'dev'
Provides-Extra: docs
Requires-Dist: myst-parser>=2.0.0; extra == 'docs'
Requires-Dist: sphinx-rtd-theme>=2.0.0; extra == 'docs'
Requires-Dist: sphinx>=7.0.0; extra == 'docs'
